bcc_rates/__init__.py
bcc_rates/__main__.py
bcc_rates/base.py
bcc_rates/bcc.py
bcc_rates/cli.py
bcc_rates/exceptions.py
bcc_rates/oxr.py
bcc_rates/utils.py
bcc_rates-1.1.0.dist-info/WHEEL
bcc_rates-1.1.0.dist-info/entry_points.txt
bcc_rates-1.1.0.dist-info/METADATA
bcc_rates-1.1.0.dist-info/RECORD
