Metadata-Version: 2.3
Name: bcc-rates
Version: 1.1.0
Summary: Currency exchange rates and converter using live data from Banque Centrale du Congo (BCC)
Author: Edimedia Mutoke
Author-email: Edimedia Mutoke <eddycondor07@gmail.com>
Requires-Dist: aiohttp>=3.13.1
Requires-Dist: beautifulsoup4>=4.14.2
Requires-Dist: dinero>=0.4.0
Requires-Dist: requests>=2.32.5
Requires-Python: >=3.12
